Metadata-Version: 2.1
Name: pxinfopkg1
Version: 0.0.1
Summary: A small example package
Home-page: UNKNOWN
Author: eGrabber
Author-email: support@egrabber.com
License: UNKNOWN
Platform: UNKNOWN
Classifier: Programming Language :: Python :: 3
Classifier: License :: OSI Approved :: MIT License
Classifier: Operating System :: OS Independent
